aiogovee/__init__.py
aiogovee/__main__.py
aiogovee/aiogovee.py
aiogovee/message.py
aiogovee/msgtypes.py
aiogovee-0.1.2.dist-info/LICENSE.txt
aiogovee-0.1.2.dist-info/METADATA
aiogovee-0.1.2.dist-info/WHEEL
aiogovee-0.1.2.dist-info/top_level.txt
aiogovee-0.1.2.dist-info/RECORD
