Metadata-Version: 2.1
Name: aiogovee
Version: 0.1.2
Summary: Python 3 /asyncio library for communication with Govee devices using their local API
Author-email: Gonzalo Parra <gaparra@gmail.com>
Project-URL: Homepage, https://github.com/Lumute/aiogovee
Project-URL: Bug Tracker, https://github.com/Lumute/aiogovee/issues
Classifier: Development Status :: 4 - Beta
Classifier: Intended Audience :: Developers
Classifier: Natural Language :: English
Classifier: Programming Language :: Python :: 3
Classifier: License :: OSI Approved :: Apache Software License
Classifier: Operating System :: OS Independent
Classifier: Topic :: Software Development :: Libraries
Requires-Python: >=3.7
License-File: LICENSE.txt
Requires-Dist: ifaddr
